<annotation>
	<folder>Geico</folder>
	<filename>256Geico.jpg</filename>
	<path>D:\shilpa\2019\PEG\Datasets\Labelled_Datasets\data_1_500_100\train\Geico\256Geico.jpg</path>
	<source>
		<database>Unknown</database>
	</source>
	<size>
		<width>300</width>
		<height>183</height>
		<depth>3</depth>
	</size>
	<segmented>0</segmented>
	<object>
		<name>Geico</name>
		<pose>Unspecified</pose>
		<truncated>0</truncated>
		<difficult>0</difficult>
		<bndbox>
			<xmin>27</xmin>
			<ymin>95</ymin>
			<xmax>125</xmax>
			<ymax>127</ymax>
		</bndbox>
	</object>
	<object>
		<name>Geico</name>
		<pose>Unspecified</pose>
		<truncated>0</truncated>
		<difficult>0</difficult>
		<bndbox>
			<xmin>229</xmin>
			<ymin>42</ymin>
			<xmax>287</xmax>
			<ymax>85</ymax>
		</bndbox>
	</object>
</annotation>
