<annotation>
	<folder>Geico</folder>
	<filename>399Geico.jpg</filename>
	<path>D:\shilpa\2019\PEG\Datasets\Labelled_Datasets\data-1_500_100\train\Geico\399Geico.jpg</path>
	<source>
		<database>Unknown</database>
	</source>
	<size>
		<width>640</width>
		<height>459</height>
		<depth>3</depth>
	</size>
	<segmented>0</segmented>
	<object>
		<name>geico</name>
		<pose>Unspecified</pose>
		<truncated>0</truncated>
		<difficult>0</difficult>
		<bndbox>
			<xmin>317</xmin>
			<ymin>9</ymin>
			<xmax>470</xmax>
			<ymax>98</ymax>
		</bndbox>
	</object>
	<object>
		<name>geico</name>
		<pose>Unspecified</pose>
		<truncated>0</truncated>
		<difficult>0</difficult>
		<bndbox>
			<xmin>395</xmin>
			<ymin>121</ymin>
			<xmax>566</xmax>
			<ymax>194</ymax>
		</bndbox>
	</object>
</annotation>
