<annotation>
	<folder>Geico</folder>
	<filename>437Geico.jpg</filename>
	<path>D:\shilpa\2019\PEG\Datasets\Labelled_Datasets\data-1_500_100\train\Geico\437Geico.jpg</path>
	<source>
		<database>Unknown</database>
	</source>
	<size>
		<width>1024</width>
		<height>547</height>
		<depth>3</depth>
	</size>
	<segmented>0</segmented>
	<object>
		<name>geico</name>
		<pose>Unspecified</pose>
		<truncated>0</truncated>
		<difficult>0</difficult>
		<bndbox>
			<xmin>753</xmin>
			<ymin>319</ymin>
			<xmax>979</xmax>
			<ymax>378</ymax>
		</bndbox>
	</object>
</annotation>
